{
  "he": {
    "mainTitle": "קבוצת פריזט",
    "subtitle": "בונים עתיד לנפגעי טראומה ובני משפחותיהם בישראל",
    "description": "קבוצת פריזט פועלת בצומת שבין נדל״ן, אימפקט חברתי ופילנתרופיה – מתוך חזון להקים בישראל מרכזים שיקומיים חדשניים לנפגעי נפש וטראומה, המבוססים על מודל נדל״ן בר־קיימא.\n\nהקבוצה יוזמת, מקדמת ומנהלת מתחמים חווייתיים המשלבים מסחר, דיור מוגן, מגורים להשכרה לטווח ארוך ומלונאות – לצד מרכזי שיקום מתקדמים המעניקים מענה הוליסטי לנפגעי טראומה מכוחות הביטחון ולאזרחים כאחד.\n\nבשנת 2024, בעקבות נפילתו של יקירנו איתי פריזט ז״ל במלחמת 7/10, הרחיבה הקבוצה את פעילותה לתחום הסולידריות החברתית הגלובלית. במהלך 2025 רכשה הקבוצה את מלוא האחזקות ב-Foundation for Israel Lovers USA, הפועלת לחיזוק הקשר בין מדינת ישראל לתומכיה ברחבי העולם, למען שיקום והעצמת קהילות ישראל.\n\nהקבוצה בונה שותפויות אסטרטגיות עם חברות ותאגידים, עמותות, ארגונים וגופים ציבוריים וממשלתיים, במטרה להקים מיזמים רפואיים-חווייתיים מבוססי נדל״ן, הפועלים באחריות כלכלית ומתוך שליחות חברתית עמוקה.\n\nהעשייה שלנו משלבת אחריות עסקית, חדשנות תכנונית ואימפקט חברתי מדיד – מתוך מחויבות לבניית עתיד יציב ובריא יותר עבור נפגעי הטראומה ובני משפחותיהם."
  },
  "en": {
    "mainTitle": "Parizat Foundation",
    "subtitle": "Building a future for the injured and their families in Israel",
    "description": "Parizat Group operates at the intersection of real estate, social impact, and philanthropy - driven by a vision to establish innovative rehabilitation centers in Israel for individuals affected by trauma and mental health challenges, based on a sustainable real estate model.\n\nThe group initiates, promotes, and manages experiential complexes that integrate commercial spaces, assisted living, long-term rental housing, and hospitality — alongside advanced rehabilitation centers that provide a holistic response to trauma survivors from the security forces and civilians alike.\n\nIn 2024, following the fall of our beloved Itay Prizet of blessed memory in the October 7th war, the group expanded its activities into the field of global social solidarity. In 2025, the group acquired full ownership of the Foundation for Israel Lovers USA, which works to strengthen the bond between the State of Israel and its supporters worldwide, in order to rehabilitate and empower Israeli communities.\n\nThe group builds strategic partnerships with companies and corporations, non-profit organizations, public institutions, and governmental bodies, with the goal of establishing real estate–based medical and experiential initiatives that operate with economic responsibility and a deep sense of social mission.\n\nOur work combines business responsibility, planning innovation, and measurable social impact — driven by a commitment to building a stronger, healthier future for trauma survivors and their families."
  }
}
